{"Kinshasa": {"lat": -4.317, "lon": 15.317}, "Arbil": {"lat": 36.333, "lon": 44.017}, "El Aai%C3%BAn": {"lat": 27.15, "lon": -13.2}, "Gaziantep": {"lat": 37.067, "lon": 37.383}, "Geelong": {"lat": -38.15, "lon": 144.35}, "Yaren District": {"lat": -0.55, "lon": 166.917}, "St. George%27s": {"lat": 12.05, "lon": -61.75}, "Chennai": {"lat": 13.083, "lon": 80.267}, "Livingstone": {"lat": -17.85, "lon": 25.867}, "Ipoh": {"lat": 4.6, "lon": 101.067}, "El Paso": {"lat": 31.783, "lon": -106.417}, "Zapopan": {"lat": 20.767, "lon": -103.4}, "Atlanta": {"lat": 33.75, "lon": -84.383}, "Ahmedabad": {"lat": 23.017, "lon": 72.567}, "Tripoli": {"lat": 32.9, "lon": 13.183}, "Kigali": {"lat": -1.933, "lon": 30.05}, "Yellowknife": {"lat": 62.45, "lon": -114.4}, "Nanning": {"lat": 22.817, "lon": 108.317}, "Port Blair": {"lat": 11.667, "lon": 92.75}, "Lubumbashi": {"lat": -11.667, "lon": 27.467}, "Accra": {"lat": 5.55, "lon": -0.2}, "Bamako": {"lat": 12.65, "lon": -8.0}, "Virginia Beach": {"lat": 36.85, "lon": -75.983}, "Charlotte": {"lat": 35.2, "lon": -80.817}, "Kanpur": {"lat": 26.45, "lon": 80.333}, "Macau": {"lat": 22.167, "lon": 113.55}, "Horta (Azores)": {"lat": 38.533, "lon": -28.633}, "Brisbane": {"lat": -27.467, "lon": 153.017}, "Osaka": {"lat": 34.683, "lon": 135.5}, "Balikpapan": {"lat": -1.25, "lon": 116.817}, "Vilnius": {"lat": 54.683, "lon": 25.283}, "Mecca": {"lat": 21.417, "lon": 39.817}, "Boa Vista": {"lat": 2.817, "lon": -60.65}, "Z%C3%BCrich": {"lat": 47.367, "lon": 8.55}, "Ulan Bator": {"lat": 47.917, "lon": 106.917}, "Denver": {"lat": 39.733, "lon": -104.983}, "Amritsar": {"lat": 31.633, "lon": 74.85}, "Ho Chi Minh City": {"lat": 10.767, "lon": 106.683}, "Curitiba": {"lat": -25.417, "lon": -49.25}, "Thimphu": {"lat": 27.467, "lon": 89.633}, "Mandurah": {"lat": -32.517, "lon": 115.717}, "Linz": {"lat": 48.3, "lon": 14.283}, "Sana%27a": {"lat": 15.35, "lon": 44.2}, "Guangzhou": {"lat": 23.1, "lon": 113.267}, "Adamstown": {"lat": -25.067, "lon": -130.1}, "Bratislava": {"lat": 48.133, "lon": 17.1}, "Hamilton": {"lat": -37.783, "lon": 175.283}, "Honolulu": {"lat": 21.3, "lon": -157.817}, "Bern": {"lat": 46.95, "lon": 7.45}, "Kaesong": {"lat": 37.967, "lon": 126.55}, "Omdurman": {"lat": 15.65, "lon": 32.483}, "Ibadan": {"lat": 7.367, "lon": 3.883}, "Bogor": {"lat": -6.6, "lon": 106.8}, "Porto Velho": {"lat": -8.75, "lon": -63.9}, "Francistown": {"lat": -21.167, "lon": 27.5}, "Rabat": {"lat": 34.033, "lon": -6.833}, "Ibiza": {"lat": 39.633, "lon": 1.717}, "Stuttgart": {"lat": 48.767, "lon": 9.167}, "Dammam": {"lat": 26.433, "lon": 50.117}, "Libreville": {"lat": 0.383, "lon": 9.45}, "Blantyre": {"lat": -15.783, "lon": 35.0}, "Oklahoma City": {"lat": 35.467, "lon": -97.533}, "Cotonou": {"lat": 6.35, "lon": 2.417}, "Ashgabat": {"lat": 37.967, "lon": 58.333}, "Quezon City": {"lat": 14.633, "lon": 121.033}, "Andorra la Vella": {"lat": 42.5, "lon": 1.5}, "Tucson": {"lat": 32.2, "lon": -110.917}, "Las Vegas": {"lat": 36.167, "lon": -115.133}, "Malm%C3%B6": {"lat": 55.583, "lon": 13.033}, "Sacramento": {"lat": 38.55, "lon": -121.467}, "Lyon": {"lat": 45.767, "lon": 4.833}, "Greenwich": {"lat": 51.467, "lon": -0.0}, "Istanbul": {"lat": 41.0, "lon": 28.967}, "Ciudad del Este": {"lat": -25.417, "lon": -54.617}, "Cayenne": {"lat": 4.917, "lon": -52.317}, "Yekaterinburg": {"lat": 56.833, "lon": 60.583}, "Dar es Salaam": {"lat": -6.817, "lon": 39.267}, "Providence": {"lat": 41.817, "lon": -71.417}, "Louisville": {"lat": 38.25, "lon": -85.75}, "Manila": {"lat": 14.583, "lon": 120.967}, "Nice": {"lat": 43.7, "lon": 7.267}, "Columbus": {"lat": 39.983, "lon": -82.983}, "Luanda": {"lat": -8.833, "lon": 13.233}, "Dibrugarh": {"lat": 27.467, "lon": 94.9}, "Niamey": {"lat": 13.517, "lon": 2.1}, "Frankfurt": {"lat": 50.1, "lon": 8.683}, "Skopje": {"lat": 42.0, "lon": 21.433}, "Hong Kong": {"lat": 22.3, "lon": 114.2}, "Kandahar": {"lat": 31.617, "lon": 65.717}, "Macap%C3%A1": {"lat": 0.033, "lon": -51.05}, "Hyderabad": {"lat": 17.367, "lon": 78.467}, "Stepanakert": {"lat": 39.817, "lon": 46.75}, "Zanzibar City": {"lat": -6.167, "lon": 39.2}, "Bilbao": {"lat": 43.25, "lon": -2.917}, "Wonsan": {"lat": 39.15, "lon": 127.433}, "Timbuktu": {"lat": 16.767, "lon": -3.0}, "Sucre": {"lat": -19.033, "lon": -65.25}, "Adana": {"lat": 37.0, "lon": 35.317}, "Montreal": {"lat": 45.5, "lon": -73.55}, "Yerevan": {"lat": 40.183, "lon": 44.517}, "Port Moresby": {"lat": -9.467, "lon": 147.167}, "Toulouse": {"lat": 43.6, "lon": 1.433}, "Angra do Hero%C3%ADsmo": {"lat": 38.65, "lon": -27.217}, "Ambon": {"lat": -3.7, "lon": 128.167}, "Bursa": {"lat": 40.183, "lon": 29.067}, "Birmingham": {"lat": 52.483, "lon": -1.883}, "Madrid": {"lat": 40.4, "lon": -3.683}, "Santiago de Cuba": {"lat": 20.017, "lon": -75.8}, "Port Hedland": {"lat": -20.3, "lon": 118.6}, "Mexicali": {"lat": 32.667, "lon": -115.467}, "Antwerp": {"lat": 51.217, "lon": 4.4}, "Thi%C3%A8s": {"lat": 14.833, "lon": -17.1}, "Tampere": {"lat": 61.5, "lon": 23.75}, "Cork (city)": {"lat": 51.883, "lon": -8.467}, "Chi%C5%9Fin%C4%83u": {"lat": 47.0, "lon": 28.867}, "Bandar Seri Begawan": {"lat": 4.883, "lon": 114.933}, "Cleveland": {"lat": 41.483, "lon": -81.667}, "Pattaya": {"lat": 12.917, "lon": 100.867}, "Glasgow": {"lat": 55.85, "lon": -4.25}, "Willemstad": {"lat": 12.117, "lon": -68.933}, "Dresden": {"lat": 51.05, "lon": 13.733}, "Chaguanas": {"lat": 10.5, "lon": -61.383}, "Zagreb": {"lat": 45.817, "lon": 15.983}, "Arequipa": {"lat": -16.4, "lon": -71.533}, "Hargeisa": {"lat": 9.5, "lon": 44.0}, "Funafuti": {"lat": -8.517, "lon": 179.217}, "Campo Grande": {"lat": -20.433, "lon": -54.633}, "Dhaka": {"lat": 23.7, "lon": 90.367}, "Novosibirsk": {"lat": 55.017, "lon": 82.933}, "Yaound%C3%A9": {"lat": 3.867, "lon": 11.517}, "Melekeok": {"lat": 7.5, "lon": 134.617}, "Saskatoon": {"lat": 52.117, "lon": -106.65}, "Bandung": {"lat": -6.95, "lon": 107.567}, "Managua": {"lat": 12.133, "lon": -86.25}, "M%C3%A1laga": {"lat": 36.717, "lon": -4.417}, "Antananarivo": {"lat": -18.933, "lon": 47.517}, "Magadan": {"lat": 59.567, "lon": 150.8}, "Puerto Williams": {"lat": 54.933, "lon": -67.617}, "Kawasaki": {"lat": 35.517, "lon": 139.7}, "Road Town": {"lat": 18.433, "lon": -64.617}, "St. Louis": {"lat": 38.617, "lon": -90.183}, "Port-au-Prince": {"lat": 18.533, "lon": -72.333}, "Dili": {"lat": -8.55, "lon": 125.583}, "Phoenix": {"lat": 33.433, "lon": -112.067}, "Belgrade": {"lat": 44.817, "lon": 20.45}, "Moroni": {"lat": -11.75, "lon": 43.2}, "Jinan": {"lat": 36.667, "lon": 116.983}, "Aarhus": {"lat": 56.15, "lon": 10.2}, "Santo Domingo": {"lat": 18.483, "lon": -69.917}, "Taiyuan": {"lat": 37.867, "lon": 112.55}, "Split (city)": {"lat": 43.5, "lon": 16.433}, "Mamoudzou": {"lat": -12.783, "lon": 45.217}, "Santa Cruz de la Sierra": {"lat": -17.8, "lon": -63.167}, "Belize City": {"lat": 17.483, "lon": -88.183}, "Monterrey": {"lat": 25.667, "lon": -100.3}, "Manchester": {"lat": 53.467, "lon": -2.233}, "Regina": {"lat": 50.433, "lon": -104.617}, "Cartagena": {"lat": 10.4, "lon": -75.5}, "Handan": {"lat": 36.6, "lon": 114.483}, "Nuuk": {"lat": 64.167, "lon": -51.75}, "Rio de Janeiro": {"lat": -22.9, "lon": -43.233}, "Tirana": {"lat": 41.317, "lon": 19.817}, "Perth": {"lat": -31.95, "lon": 115.85}, "Munich": {"lat": 48.133, "lon": 11.567}, "Shillong": {"lat": 25.567, "lon": 91.883}, "Beirut": {"lat": 33.883, "lon": 35.5}, "Simferopol": {"lat": 44.95, "lon": 34.1}, "Wuhan": {"lat": 30.567, "lon": 114.267}, "Brikama": {"lat": 13.267, "lon": -16.65}, "Bangui": {"lat": 4.35, "lon": 18.583}, "Malabo": {"lat": 3.75, "lon": 8.767}, "Maracaibo": {"lat": -10.65, "lon": -71.633}, "Harbin": {"lat": 45.75, "lon": 126.633}, "Hamburg": {"lat": 53.583, "lon": 9.983}, "Shigatse": {"lat": 29.267, "lon": 88.867}, "Brussels": {"lat": 50.833, "lon": 4.35}, "Porto": {"lat": 41.15, "lon": -8.633}, "Dubai": {"lat": 25.267, "lon": 55.3}, "Addis Ababa": {"lat": 9.017, "lon": 38.733}, "Chu%C3%AD": {"lat": -33.683, "lon": -53.45}, "Miami": {"lat": 25.783, "lon": -80.217}, "Anadyr (town)": {"lat": 64.733, "lon": 177.5}, "Phnom Penh": {"lat": 11.55, "lon": 104.917}, "Rome": {"lat": 41.9, "lon": 12.5}, "Nassau": {"lat": 25.05, "lon": -77.333}, "Marseille": {"lat": 43.3, "lon": 5.367}, "Mogadishu": {"lat": 2.033, "lon": 45.35}, "Malacca Town": {"lat": 2.183, "lon": 102.383}, "Avarua": {"lat": -21.2, "lon": -159.767}, "S%C3%A3o Jos%C3%A9 dos Campos": {"lat": -23.183, "lon": -45.867}, "Siem Reap": {"lat": 13.35, "lon": 103.85}, "Pontianak": {"lat": 0.0, "lon": 109.333}, "Sitka": {"lat": 57.05, "lon": -135.317}, "Cairo": {"lat": 30.05, "lon": 31.217}, "Shenyang": {"lat": 41.783, "lon": 123.45}, "Agartala": {"lat": 23.5, "lon": 91.2}, "Abidjan": {"lat": 5.333, "lon": -4.017}, "Seville": {"lat": 37.367, "lon": -5.983}, "Milan": {"lat": 45.467, "lon": 9.183}, "Nuku%CA%BBalofa": {"lat": -21.133, "lon": -175.2}, "Sri Jayawardenapura-Kotte": {"lat": 6.9, "lon": 79.883}, "Stanley": {"lat": 51.683, "lon": -57.85}, "Edmonton": {"lat": 53.567, "lon": -113.517}, "Patna": {"lat": 25.6, "lon": 85.133}, "Hanover": {"lat": 52.367, "lon": 9.717}, "Harare": {"lat": -17.817, "lon": 31.05}, "Mbabane": {"lat": -26.317, "lon": 31.133}, "Perm": {"lat": 58.0, "lon": 56.317}, "Rawalpindi": {"lat": 33.6, "lon": 73.033}, "Johor Bahru": {"lat": 1.483, "lon": 103.733}, "Jamestown": {"lat": -15.917, "lon": -5.733}, "Bissau": {"lat": 11.85, "lon": -15.583}, "Hag%C3%A5t%C3%B1a": {"lat": 13.483, "lon": 144.75}, "Gangtok": {"lat": 27.317, "lon": 88.617}, "Miri": {"lat": 4.383, "lon": 113.967}, "Quebec City": {"lat": 46.8, "lon": -71.217}, "Davao City": {"lat": 7.5, "lon": 126.0}, "Praia": {"lat": 14.917, "lon": -23.517}, "Omsk": {"lat": 54.983, "lon": 73.367}, "Anchorage": {"lat": 61.217, "lon": -149.883}, "Surat Thani": {"lat": 9.133, "lon": 99.333}, "Conakry": {"lat": 9.517, "lon": -13.7}, "Palembang": {"lat": -2.983, "lon": 104.75}, "Astana": {"lat": 51.183, "lon": 71.45}, "Kuwait City": {"lat": 29.367, "lon": 47.967}, "Lucknow": {"lat": 26.85, "lon": 80.917}, "Salzburg": {"lat": 47.8, "lon": 13.033}, "Kharkiv": {"lat": 49.917, "lon": 36.317}, "Palikir": {"lat": 6.917, "lon": 158.183}, "Hangzhou": {"lat": 30.25, "lon": 120.167}, "Barcelona": {"lat": 41.383, "lon": 2.183}, "Liverpool": {"lat": 53.4, "lon": -2.983}, "Asunci%C3%B3n": {"lat": -25.267, "lon": -57.667}, "Luxembourg (city)": {"lat": 49.6, "lon": 6.117}, "Rockhampton": {"lat": -23.367, "lon": 150.5}, "Buffalo": {"lat": 42.9, "lon": -78.85}, "Peshawar": {"lat": 34.0, "lon": 71.5}, "M%C3%A9rida": {"lat": 20.967, "lon": -89.617}, "Ushuaia": {"lat": -54.8, "lon": -68.3}, "Sukhumi": {"lat": 43.0, "lon": 41.017}, "Boston": {"lat": 42.35, "lon": -71.05}, "Baku": {"lat": 40.367, "lon": 49.883}, "Lom%C3%A9": {"lat": 6.133, "lon": 1.2}, "Adelaide": {"lat": -34.917, "lon": 138.6}, "Mexico City": {"lat": 19.4, "lon": -99.117}, "Bratsk": {"lat": 56.167, "lon": 101.617}, "Belfast": {"lat": 54.6, "lon": -5.917}, "Mendoza": {"lat": -32.883, "lon": -68.817}, "Port Said": {"lat": 31.25, "lon": 32.283}, "Hai Phong": {"lat": 20.85, "lon": 106.683}, "Whitehorse": {"lat": 60.717, "lon": -135.05}, "Brazzaville": {"lat": -4.267, "lon": 15.283}, "Maseru": {"lat": -29.3, "lon": 27.467}, "Medina": {"lat": 24.467, "lon": 39.6}, "Chihuahua": {"lat": 28.1, "lon": -106.0}, "Nukulaelae": {"lat": -9.383, "lon": 179.85}, "Dongguan": {"lat": 23.033, "lon": 113.717}, "Strasbourg": {"lat": 48.583, "lon": 7.75}, "Vit%C3%B3ria": {"lat": -20.317, "lon": -40.333}, "Saint-Denis": {"lat": -20.867, "lon": 55.45}, "Seattle": {"lat": 47.6, "lon": -122.317}, "Faisalabad": {"lat": 31.367, "lon": 72.983}, "Koror": {"lat": 7.35, "lon": 134.467}, "Helsinki": {"lat": 60.167, "lon": 24.933}, "Udon Thani": {"lat": 17.417, "lon": 102.75}, "Ottawa": {"lat": 45.417, "lon": -75.683}, "Ouagadougou": {"lat": 12.35, "lon": -1.533}, "Ilh%C3%A9us": {"lat": -14.783, "lon": -39.05}, "Podgorica": {"lat": 42.467, "lon": 19.267}, "Cannes": {"lat": 43.55, "lon": 7.0}, "Incheon": {"lat": 37.483, "lon": 126.633}, "Mwanza": {"lat": -2.517, "lon": 32.9}, "Roseau": {"lat": 15.3, "lon": -61.383}, "Canberra": {"lat": -35.3, "lon": 149.117}, "D%C3%BCsseldorf": {"lat": 51.233, "lon": 6.783}, "New Orleans": {"lat": 29.967, "lon": -90.067}, "Guwahati": {"lat": 26.167, "lon": 91.767}, "Kota Bharu": {"lat": 6.133, "lon": 102.25}, "Da Nang": {"lat": 16.067, "lon": 108.233}, "Lima": {"lat": -12.033, "lon": -77.017}, "Pelotas": {"lat": -31.767, "lon": -52.333}, "San Fernando": {"lat": 10.283, "lon": -61.467}, "Sydney": {"lat": -33.85, "lon": 151.2}, "Chicago": {"lat": 41.867, "lon": -87.617}, "Ponta Delgada": {"lat": 37.733, "lon": -25.667}, "San Salvador": {"lat": 13.683, "lon": -89.183}, "Philadelphia": {"lat": 39.95, "lon": -75.167}, "Douglas": {"lat": 54.133, "lon": -4.483}, "Cali": {"lat": 3.417, "lon": -76.517}, "Saint Petersburg": {"lat": 59.933, "lon": 30.333}, "Winnipeg": {"lat": 49.9, "lon": -97.133}, "Jayapura": {"lat": -2.533, "lon": 140.717}, "Naples": {"lat": 40.833, "lon": 14.25}, "Odessa": {"lat": 46.467, "lon": 30.733}, "Rabi Island": {"lat": 3.133, "lon": -12.05}, "Charlottetown": {"lat": 46.233, "lon": -63.133}, "Naypyidaw": {"lat": 19.75, "lon": 96.1}, "Tashkent": {"lat": 41.267, "lon": 69.217}, "Kyoto": {"lat": 35.017, "lon": 135.767}, "Nizhny Novgorod": {"lat": 56.333, "lon": 44.0}, "Okinawa": {"lat": 26.333, "lon": 127.8}, "Tskhinvali": {"lat": 42.233, "lon": 43.967}, "Guayaquil": {"lat": 2.183, "lon": -79.883}, "Las Palmas de Gran Canaria": {"lat": 28.133, "lon": -15.433}, "Chongqing": {"lat": 29.55, "lon": 106.5}, "Weno": {"lat": 7.45, "lon": 151.85}, "Pago Pago": {"lat": -14.267, "lon": -170.7}, "Jersey City": {"lat": 41.433, "lon": -74.133}, "Quetzaltenango": {"lat": 14.833, "lon": -91.517}, "Puebla": {"lat": 19.05, "lon": -98.2}, "The Valley": {"lat": 18.217, "lon": -63.05}, "Port Louis": {"lat": -20.167, "lon": 57.5}, "N%27Djamena": {"lat": 12.1, "lon": 15.05}, "Punta Arenas": {"lat": -53.167, "lon": -70.933}, "Tbilisi": {"lat": 41.717, "lon": 44.783}, "Prague": {"lat": 50.083, "lon": 14.417}, "Sofia": {"lat": 42.7, "lon": 23.333}, "Nanjing": {"lat": 32.05, "lon": 118.767}, "Bridgetown": {"lat": 13.083, "lon": -59.617}, "Iquitos": {"lat": -3.733, "lon": -73.25}, "Lisbon": {"lat": 38.7, "lon": -9.183}, "Amsterdam": {"lat": 52.367, "lon": 4.883}, "Copenhagen": {"lat": 55.667, "lon": 12.567}, "San Diego": {"lat": 32.767, "lon": -117.15}, "Basra": {"lat": 30.5, "lon": 47.817}, "Kiev": {"lat": 50.45, "lon": 30.517}, "Zhengzhou": {"lat": 34.75, "lon": 113.633}, "Paris": {"lat": 48.867, "lon": 2.333}, "Ndola": {"lat": -12.967, "lon": 28.633}, "Johannesburg": {"lat": -26.2, "lon": 28.033}, "Hilo": {"lat": 19.7, "lon": -155.1}, "Kuala Lumpur": {"lat": 3.133, "lon": 101.683}, "Abuja": {"lat": 9.067, "lon": 7.483}, "Forked River": {"lat": 39.817, "lon": -74.183}, "Tegucigalpa": {"lat": 14.083, "lon": -87.217}, "Santiago": {"lat": -33.45, "lon": -70.667}, "Longyearbyen": {"lat": 78.217, "lon": 15.55}, "Kota Kinabalu": {"lat": 5.967, "lon": 116.083}, "Abu Dhabi": {"lat": 24.467, "lon": 54.367}, "Berlin": {"lat": 52.517, "lon": 13.417}, "Campinas": {"lat": -22.9, "lon": -47.05}, "Nairobi": {"lat": -1.283, "lon": 36.817}, "Djibouti (city)": {"lat": 11.583, "lon": 43.133}, "Jaipur": {"lat": 26.917, "lon": 75.817}, "Gaborone": {"lat": -24.65, "lon": 25.9}, "Oslo": {"lat": 59.95, "lon": 10.75}, "Srinagar": {"lat": 34.083, "lon": 74.783}, "Shanghai": {"lat": 31.2, "lon": 121.5}, "Nantes": {"lat": 47.217, "lon": -1.55}, "San Jos%C3%A9": {"lat": 9.933, "lon": -84.083}, "Pune": {"lat": 18.517, "lon": 73.85}, "Havana": {"lat": 23.133, "lon": -82.383}, "Mersin": {"lat": 36.8, "lon": 34.633}, "Tabriz": {"lat": 38.083, "lon": 46.283}, "Chittagong": {"lat": 22.367, "lon": 91.8}, "Dublin": {"lat": 53.333, "lon": -6.267}, "George Town": {"lat": 5.417, "lon": 100.317}, "Banda Aceh": {"lat": 5.55, "lon": 95.317}, "Suva": {"lat": -18.133, "lon": 178.433}, "Invercargill": {"lat": -46.417, "lon": 168.3}, "Monaco": {"lat": 43.733, "lon": 7.4}, "Namangan": {"lat": 41.633, "lon": 71.967}, "Phuket (city)": {"lat": 7.883, "lon": 98.4}, "Charlotte Amalie": {"lat": -18.35, "lon": -64.95}, "Pekanbaru": {"lat": 0.533, "lon": 101.45}, "Washington": {"lat": 38.883, "lon": -77.033}, "Minneapolis": {"lat": 44.967, "lon": -93.25}, "Yamoussoukro": {"lat": 6.817, "lon": -5.283}, "Salt Lake City": {"lat": 40.75, "lon": -111.883}, "Paramaribo": {"lat": 5.867, "lon": -55.167}, "San Juan": {"lat": 18.45, "lon": -66.067}, "Reykjav%C3%ADk": {"lat": 64.133, "lon": -21.933}, "Rochester": {"lat": 43.15, "lon": -77.6}, "Caracas": {"lat": 10.5, "lon": -66.917}, "Iquique": {"lat": -20.217, "lon": -70.15}, "Zamboanga City": {"lat": 6.9, "lon": 122.067}, "Makassar": {"lat": -5.133, "lon": 119.417}, "Batticaloa": {"lat": 7.717, "lon": 81.7}, "Amman": {"lat": 31.95, "lon": 35.933}, "Ludhiana": {"lat": 30.9, "lon": 75.85}, "New York City": {"lat": 40.717, "lon": -74.0}, "Honiara": {"lat": -9.433, "lon": 159.95}, "Port of Spain": {"lat": 10.667, "lon": -61.517}, "Leeds": {"lat": 53.8, "lon": -1.55}, "Apia": {"lat": -13.833, "lon": -171.833}, "Los Angeles": {"lat": 34.05, "lon": -118.25}, "San Carlos de Bariloche": {"lat": -41.15, "lon": -71.3}, "Tehran": {"lat": 35.683, "lon": 51.417}, "Bangalore": {"lat": 12.967, "lon": 77.567}, "San Antonio": {"lat": 29.533, "lon": -98.467}, "Tamale": {"lat": 9.4, "lon": -0.85}, "Murmansk": {"lat": 68.967, "lon": 33.083}, "Koulikoro": {"lat": 12.983, "lon": -7.567}, "Sabha": {"lat": 27.033, "lon": 14.433}, "Kathmandu": {"lat": 27.7, "lon": 85.333}, "Pretoria": {"lat": -25.733, "lon": 28.183}, "Thessaloniki": {"lat": 40.633, "lon": 22.95}, "Kano": {"lat": 12.0, "lon": 8.517}, "St. John%27s": {"lat": 47.55, "lon": -52.7}, "Guatemala City": {"lat": 14.633, "lon": -90.55}, "Bergen": {"lat": 60.367, "lon": 5.4}, "Bujumbura": {"lat": -3.383, "lon": 29.367}, "Cairns": {"lat": -16.917, "lon": 145.767}, "Veracruz": {"lat": 19.183, "lon": -96.133}, "Konya": {"lat": 37.867, "lon": 32.483}, "Aberdeen": {"lat": 57.15, "lon": -2.1}, "Wollongong": {"lat": -34.433, "lon": 150.883}, "Fredericton": {"lat": 45.95, "lon": -66.667}, "Fairbanks": {"lat": 64.833, "lon": -147.7}, "Hanoi": {"lat": 21.033, "lon": 105.85}, "Gibraltar": {"lat": 36.133, "lon": -5.35}, "Lahore": {"lat": 31.55, "lon": 74.333}, "Riverside": {"lat": 33.933, "lon": -117.383}, "Malang": {"lat": -7.967, "lon": 112.617}, "Turin": {"lat": 45.067, "lon": 7.7}, "Oranjestad": {"lat": 12.517, "lon": -70.033}, "Valletta": {"lat": 35.9, "lon": 14.5}, "Manaus": {"lat": -3.1, "lon": -60.017}, "Semarang": {"lat": -6.967, "lon": 110.417}, "Khartoum": {"lat": 15.633, "lon": 32.533}, "Birkirkara": {"lat": 35.883, "lon": 14.45}, "Valpara%C3%ADso": {"lat": -33.05, "lon": -71.617}, "Assis": {"lat": -22.65, "lon": -50.4}, "Toronto": {"lat": 43.65, "lon": -79.383}, "Algiers": {"lat": 36.7, "lon": 3.217}, "Xi%27an": {"lat": 34.267, "lon": 108.9}, "Tokyo": {"lat": 35.683, "lon": 139.767}, "Islamabad": {"lat": 33.717, "lon": 73.067}, "Wellington": {"lat": -41.283, "lon": 174.767}, "Stockholm": {"lat": 59.35, "lon": 18.067}, "Tel Aviv": {"lat": 32.083, "lon": 34.8}, "Hiroshima": {"lat": 34.383, "lon": 132.45}, "Norilsk": {"lat": 69.35, "lon": 88.2}, "Concepci%C3%B3n": {"lat": -36.833, "lon": -73.05}, "Lobamba": {"lat": -26.467, "lon": 31.2}, "Jeddah": {"lat": 21.533, "lon": 39.167}, "Asmara": {"lat": 15.333, "lon": 38.933}, "Kobe": {"lat": 34.683, "lon": 135.2}, "Macei%C3%B3": {"lat": -9.65, "lon": -35.717}, "S%C3%A3o Tom%C3%A9": {"lat": 0.333, "lon": 6.683}, "Tianjin": {"lat": 39.133, "lon": 117.183}, "Port Elizabeth": {"lat": -33.95, "lon": 25.6}, "Athens": {"lat": 37.967, "lon": 23.717}, "South Tarawa": {"lat": 1.317, "lon": 172.983}, "Kabul": {"lat": 34.533, "lon": 69.167}, "Adak": {"lat": 51.883, "lon": -176.633}, "Tallinn": {"lat": 59.433, "lon": 24.75}, "Valencia": {"lat": 39.483, "lon": -0.367}, "Montevideo": {"lat": -34.917, "lon": -56.167}, "Gothenburg": {"lat": 57.7, "lon": 11.967}, "Cockburn Town": {"lat": 21.45, "lon": -71.133}, "Padang": {"lat": -0.95, "lon": 100.35}, "Nashville": {"lat": 36.167, "lon": -86.783}, "Buenos Aires": {"lat": -34.6, "lon": -58.367}, "Bras%C3%ADlia": {"lat": -15.8, "lon": -47.9}, "Lviv": {"lat": 49.85, "lon": 24.017}, "Bangkok": {"lat": 13.75, "lon": 100.483}, "Dodoma": {"lat": -6.167, "lon": 35.733}, "Cuiab%C3%A1": {"lat": -15.583, "lon": -56.083}, "Suez": {"lat": 29.967, "lon": 32.55}, "Qingdao": {"lat": 36.083, "lon": 120.333}, "Taichung": {"lat": 24.15, "lon": 120.667}, "Budapest": {"lat": 47.467, "lon": 19.05}, "Multan": {"lat": 30.2, "lon": 71.45}, "Jakarta": {"lat": -6.133, "lon": 106.75}, "Kansas City": {"lat": 39.1, "lon": -94.567}, "Calgary": {"lat": 51.033, "lon": -114.05}, "Nagpur": {"lat": 21.067, "lon": 79.017}, "%C4%B0zmir": {"lat": 38.433, "lon": 27.15}, "Raleigh": {"lat": 35.817, "lon": -78.633}, "Manzini": {"lat": -26.483, "lon": 31.367}, "La Paz": {"lat": -16.5, "lon": -68.15}, "Tijuana": {"lat": 32.517, "lon": -117.033}, "Houston": {"lat": 29.75, "lon": -95.367}, "Bulawayo": {"lat": -20.167, "lon": 28.567}, "Makati City": {"lat": 14.55, "lon": 121.033}, "Durango": {"lat": 24.017, "lon": -104.667}, "Krak%C3%B3w": {"lat": 50.05, "lon": 19.933}, "Hat Yai": {"lat": 7.017, "lon": 100.467}, "Lagos": {"lat": 6.45, "lon": 3.383}, "Colombo": {"lat": 6.883, "lon": 79.867}, "Yokohama": {"lat": 35.45, "lon": 139.633}, "Milwaukee": {"lat": 47.05, "lon": -87.95}, "Portland": {"lat": 45.517, "lon": -122.667}, "Jerusalem": {"lat": 31.783, "lon": 35.217}, "Sapporo": {"lat": 43.067, "lon": 141.35}, "Espoo": {"lat": 60.2, "lon": 24.65}, "Denpasar": {"lat": -8.65, "lon": 115.217}, "Kingstown": {"lat": 13.167, "lon": -61.233}, "Fortaleza": {"lat": -3.767, "lon": -38.567}, "San Francisco": {"lat": 37.767, "lon": -122.417}, "Nicosia": {"lat": 35.167, "lon": 33.35}, "Rosario": {"lat": -32.95, "lon": -60.667}, "Shenzhen": {"lat": 22.55, "lon": 114.1}, "Saint John": {"lat": 45.267, "lon": -66.05}, "Tiraspol": {"lat": 46.85, "lon": 29.633}, "Bloemfontein": {"lat": -29.1, "lon": 26.217}, "Dunedin": {"lat": -45.867, "lon": 170.5}, "Innsbruck": {"lat": 47.267, "lon": 11.383}, "Victoria": {"lat": -4.617, "lon": 55.45}, "Baghdad": {"lat": 33.317, "lon": 44.417}, "Taipei": {"lat": 25.033, "lon": 121.633}, "Kandy": {"lat": 7.283, "lon": 80.633}, "Newcastle": {"lat": -32.917, "lon": 151.75}, "Medell%C3%ADn": {"lat": 6.233, "lon": -75.567}, "Tampa": {"lat": 27.967, "lon": -82.467}, "Fukuoka": {"lat": 33.583, "lon": 130.4}, "Iloilo City": {"lat": 10.683, "lon": 122.55}, "La Serena": {"lat": -29.9, "lon": -71.25}, "Ljubljana": {"lat": 46.067, "lon": 14.5}, "Christchurch": {"lat": -43.533, "lon": 172.617}, "Surat": {"lat": 21.167, "lon": 72.817}, "T%C3%B3rshavn": {"lat": 62.0, "lon": -6.783}, "Valdivia": {"lat": -39.817, "lon": -73.233}, "Alexandria": {"lat": 31.2, "lon": 29.917}, "Cincinnati": {"lat": 39.133, "lon": -84.5}, "Casablanca": {"lat": 33.533, "lon": -7.583}, "Cologne": {"lat": 50.95, "lon": 6.967}, "London": {"lat": 51.5, "lon": -0.117}, "Chiang Mai": {"lat": 18.783, "lon": 98.983}, "Mashhad": {"lat": 36.3, "lon": 59.6}, "Douala": {"lat": 4.05, "lon": 9.7}, "Hu%E1%BA%BF": {"lat": 16.467, "lon": 107.6}, "Rio Branco": {"lat": -10.117, "lon": -69.35}, "Yangon": {"lat": 16.8, "lon": 96.167}, "Auckland": {"lat": -36.85, "lon": 174.783}, "Dededo": {"lat": 13.517, "lon": 144.833}, "Santa Cruz de Tenerife": {"lat": 28.467, "lon": -16.25}, "Saint-Pierre": {"lat": 46.767, "lon": -56.167}, "Kaohsiung": {"lat": 22.633, "lon": 120.267}, "Kolkata": {"lat": 22.567, "lon": 88.367}, "Vienna": {"lat": 48.2, "lon": 16.367}, "Saipan": {"lat": 15.183, "lon": 145.75}, "Edinburgh": {"lat": 55.95, "lon": -3.15}, "Labasa": {"lat": -16.433, "lon": 179.367}, "Seoul": {"lat": 37.55, "lon": 126.983}, "Singapore": {"lat": 1.367, "lon": 103.8}, "Pittsburgh": {"lat": 40.433, "lon": -79.967}, "Pristina": {"lat": 42.667, "lon": 21.167}, "Hanga Roa": {"lat": 27.15, "lon": -109.433}, "Alofi": {"lat": -19.05, "lon": -169.917}, "Albuquerque": {"lat": 35.1, "lon": -106.6}, "Muscat": {"lat": 23.6, "lon": 58.533}, "Palma": {"lat": 39.567, "lon": 2.65}, "Serekunda": {"lat": 13.433, "lon": -16.667}, "Karachi": {"lat": 24.85, "lon": 67.0}, "Graz": {"lat": 47.067, "lon": 15.433}, "Majuro": {"lat": 7.067, "lon": 171.267}, "Freetown": {"lat": 8.467, "lon": -13.267}, "Petropavlovsk-Kamchatsky": {"lat": 53.017, "lon": 158.65}, "Cape Town": {"lat": -33.917, "lon": 18.417}, "Shijiazhuang": {"lat": 38.033, "lon": 114.5}, "Monrovia": {"lat": 6.317, "lon": -10.767}, "Indianapolis": {"lat": 39.783, "lon": -86.15}, "Vatican City": {"lat": 41.9, "lon": 12.45}, "Panama City": {"lat": 8.983, "lon": -79.517}, "Enugu": {"lat": 6.45, "lon": 7.5}, "New Delhi": {"lat": 28.617, "lon": 77.2}, "Bel%C3%A9m": {"lat": 1.467, "lon": -48.483}, "Tagbilaran": {"lat": 9.65, "lon": 123.85}, "Tartu": {"lat": 58.383, "lon": 26.717}, "Basse-Terre": {"lat": 15.983, "lon": -61.717}, "Nukus": {"lat": 42.467, "lon": 59.6}, "City of San Marino": {"lat": 43.933, "lon": 12.433}, "Busan": {"lat": 35.1, "lon": 129.033}, "Nagoya": {"lat": 35.183, "lon": 136.9}, "Lusaka": {"lat": -15.417, "lon": 28.283}, "Vientiane": {"lat": 17.95, "lon": 102.617}, "Antofagasta": {"lat": -23.65, "lon": -70.4}, "Dallas": {"lat": 32.767, "lon": -96.8}, "C%C3%B3rdoba": {"lat": -31.4, "lon": -64.183}, "Surabaya": {"lat": -7.233, "lon": 112.733}, "Xining": {"lat": 36.633, "lon": 101.767}, "Manama": {"lat": 26.217, "lon": 50.583}, "City of Halifax": {"lat": 44.667, "lon": -63.6}, "Vladivostok": {"lat": 43.133, "lon": 131.9}, "Bogot%C3%A1": {"lat": 4.6, "lon": -74.067}, "Castries": {"lat": 14.017, "lon": -60.983}, "Chongjin": {"lat": 41.8, "lon": 129.783}, "Nakhon Ratchasima": {"lat": 14.967, "lon": 102.1}, "Rotterdam": {"lat": 51.933, "lon": 4.467}, "Almaty": {"lat": 43.267, "lon": 76.883}, "Lanzhou": {"lat": 36.033, "lon": 103.8}, "Mal%C3%A9": {"lat": 4.167, "lon": 73.5}, "Durban": {"lat": -29.883, "lon": 31.05}, "Marrakech": {"lat": 31.633, "lon": -8.0}, "Port Vila": {"lat": -17.75, "lon": 168.3}, "Kunming": {"lat": 25.067, "lon": 102.683}, "Yogyakarta (city)": {"lat": -7.8, "lon": 110.367}, "Noum%C3%A9a": {"lat": -22.267, "lon": 166.45}, "Hobart": {"lat": -42.883, "lon": 147.317}, "Bishkek": {"lat": 42.867, "lon": 74.6}, "S%C3%A3o Paulo": {"lat": -23.55, "lon": -46.633}, "Yakutsk": {"lat": 62.033, "lon": 129.733}, "Detroit": {"lat": 42.333, "lon": -83.05}, "Tunis": {"lat": 36.8, "lon": 10.167}, "Guadalajara": {"lat": 20.667, "lon": -103.35}, "Lilongwe": {"lat": -13.983, "lon": 33.783}, "Austin": {"lat": 30.267, "lon": -97.767}, "Bucharest": {"lat": 44.433, "lon": 26.1}, "Beijing": {"lat": 39.9, "lon": 116.4}, "Doha": {"lat": 25.283, "lon": 51.533}, "The Hague": {"lat": 52.067, "lon": 4.3}, "Damascus": {"lat": 33.5, "lon": 36.283}, "Memphis": {"lat": 35.117, "lon": -89.967}, "Riyadh": {"lat": 24.7, "lon": 46.717}, "Mumbai": {"lat": 18.95, "lon": 72.817}, "Kaliningrad": {"lat": 54.717, "lon": 20.517}, "Fort-de-France": {"lat": 14.6, "lon": -61.083}, "Townsville": {"lat": -19.25, "lon": 146.817}, "Kingston": {"lat": -29.067, "lon": 167.967}, "Calama": {"lat": -22.467, "lon": -68.933}, "Riga": {"lat": 56.967, "lon": 24.133}, "Dushanbe": {"lat": 38.533, "lon": 68.767}, "Maputo": {"lat": -25.967, "lon": 32.583}, "Lhasa": {"lat": 29.65, "lon": 91.117}, "Dakar": {"lat": 14.683, "lon": -17.433}, "Vancouver": {"lat": 49.25, "lon": -123.1}, "Gaza": {"lat": 31.517, "lon": 34.45}, "Porto Alegre": {"lat": 30.033, "lon": -51.217}, "Darwin": {"lat": -12.45, "lon": 130.833}, "%C3%9Cr%C3%BCmqi": {"lat": 43.8, "lon": 87.583}, "Geneva": {"lat": 46.2, "lon": 6.15}, "Changchun": {"lat": 43.883, "lon": 125.317}, "Ankara": {"lat": 39.867, "lon": 32.833}, "Daegu": {"lat": 35.867, "lon": 128.6}, "Barranquilla": {"lat": 10.95, "lon": -74.783}, "Gold Coast": {"lat": -28.167, "lon": 153.55}, "Jacksonville": {"lat": 30.317, "lon": -81.65}, "Medan": {"lat": 3.583, "lon": 98.667}, "Kuching": {"lat": 1.55, "lon": 110.35}, "Belmopan": {"lat": 17.25, "lon": -88.767}, "Cusco": {"lat": -13.5, "lon": -71.967}, "Vaduz": {"lat": 47.133, "lon": 9.517}, "Sarajevo": {"lat": 43.85, "lon": 18.35}, "Wichita": {"lat": 37.683, "lon": -97.333}, "Porto-Novo": {"lat": 6.5, "lon": 2.6}, "Melbourne": {"lat": -37.8, "lon": 144.95}, "Cardiff": {"lat": 51.483, "lon": -3.183}, "Minsk": {"lat": 53.9, "lon": 27.567}, "Recife": {"lat": -8.067, "lon": -34.867}, "Alor Star": {"lat": 6.117, "lon": 100.367}, "Luxor": {"lat": 25.683, "lon": 32.65}, "Baltimore": {"lat": 39.283, "lon": -76.617}, "Quito": {"lat": 0.25, "lon": -78.583}, "Mata-Utu": {"lat": -13.283, "lon": 176.183}, "Iqaluit": {"lat": 63.75, "lon": -68.517}, "Dalian": {"lat": 39.033, "lon": 121.767}, "Chengdu": {"lat": 30.65, "lon": 104.067}, "Banjul": {"lat": 13.45, "lon": -16.567}, "Papeete": {"lat": -17.533, "lon": -149.567}, "Leipzig": {"lat": 51.333, "lon": 12.383}, "Samara": {"lat": 53.233, "lon": 50.167}, "Gda%C5%84sk": {"lat": 54.35, "lon": 18.667}, "Nouakchott": {"lat": 18.1, "lon": -15.95}, "Pyongyang": {"lat": 39.033, "lon": 125.75}, "Juneau": {"lat": 58.35, "lon": -134.5}, "Cebu City": {"lat": 10.283, "lon": 123.9}, "Bah%C3%ADa Blanca": {"lat": -38.717, "lon": -62.267}, "Moscow": {"lat": 55.75, "lon": 37.6}, "Warsaw": {"lat": 52.233, "lon": 21.0}}